MANIFEST.in
NOTICE
requirements.txt
setup.cfg
setup.py
DevLGram/__init__.py
DevLGram.egg-info/PKG-INFO
DevLGram.egg-info/SOURCES.txt
DevLGram.egg-info/dependency_links.txt
DevLGram.egg-info/not-zip-safe
DevLGram.egg-info/requires.txt
DevLGram.egg-info/top_level.txt
DevLGram/api/__init__.py
DevLGram/api/all.py
DevLGram/api/core/__init__.py
DevLGram/api/core/future_salt.py
DevLGram/api/core/future_salts.py
DevLGram/api/core/gzip_packed.py
DevLGram/api/core/message.py
DevLGram/api/core/msg_container.py
DevLGram/api/core/object.py
DevLGram/api/core/primitives/__init__.py
DevLGram/api/core/primitives/bool.py
DevLGram/api/core/primitives/bytes.py
DevLGram/api/core/primitives/double.py
DevLGram/api/core/primitives/int.py
DevLGram/api/core/primitives/null.py
DevLGram/api/core/primitives/string.py
DevLGram/api/core/primitives/vector.py
DevLGram/api/functions/__init__.py
DevLGram/api/functions/destroy_auth_key.py
DevLGram/api/functions/destroy_session.py
DevLGram/api/functions/get_future_salts.py
DevLGram/api/functions/init_connection.py
DevLGram/api/functions/invoke_after_msg.py
DevLGram/api/functions/invoke_after_msgs.py
DevLGram/api/functions/invoke_with_layer.py
DevLGram/api/functions/invoke_with_messages_range.py
DevLGram/api/functions/invoke_with_takeout.py
DevLGram/api/functions/invoke_without_updates.py
DevLGram/api/functions/ping.py
DevLGram/api/functions/ping_delay_disconnect.py
DevLGram/api/functions/req_dh_params.py
DevLGram/api/functions/req_pq.py
DevLGram/api/functions/req_pq_multi.py
DevLGram/api/functions/rpc_drop_answer.py
DevLGram/api/functions/set_client_dh_params.py
DevLGram/api/functions/account/__init__.py
DevLGram/api/functions/account/accept_authorization.py
DevLGram/api/functions/account/cancel_password_email.py
DevLGram/api/functions/account/change_phone.py
DevLGram/api/functions/account/check_username.py
DevLGram/api/functions/account/confirm_password_email.py
DevLGram/api/functions/account/confirm_phone.py
DevLGram/api/functions/account/delete_account.py
DevLGram/api/functions/account/delete_secure_value.py
DevLGram/api/functions/account/finish_takeout_session.py
DevLGram/api/functions/account/get_account_ttl.py
